README.txt
setup.cfg
setup.py
vmsutils/__init__.py
vmsutils/kvmvalues.py
vmsutils.egg-info/PKG-INFO
vmsutils.egg-info/SOURCES.txt
vmsutils.egg-info/dependency_links.txt
vmsutils.egg-info/entry_points.txt
vmsutils.egg-info/not-zip-safe
vmsutils.egg-info/top_level.txt