Metadata-Version: 1.0
Name: vmsutils
Version: 0.1dev
Summary: Utilities for virtual machines
Home-page: UNKNOWN
Author: Fredo le geek
Author-email: flg at fredolegeek.org
License: GPL
Platform: UNKNOWN
